iceberg_mcp_server/__init__.py
iceberg_mcp_server/server.py
iceberg_mcp_server/tools/__init__.py
iceberg_mcp_server/tools/impala_tools.py
iflow_mcp_cloudera_iceberg_mcp_server-0.1.0.dist-info/METADATA
iflow_mcp_cloudera_iceberg_mcp_server-0.1.0.dist-info/WHEEL
iflow_mcp_cloudera_iceberg_mcp_server-0.1.0.dist-info/entry_points.txt
iflow_mcp_cloudera_iceberg_mcp_server-0.1.0.dist-info/licenses/LICENSE
iflow_mcp_cloudera_iceberg_mcp_server-0.1.0.dist-info/licenses/NOTICE.txt
iflow_mcp_cloudera_iceberg_mcp_server-0.1.0.dist-info/RECORD
