Metadata-Version: 2.4
Name: iflow-mcp_cloudera_iceberg-mcp-server
Version: 0.1.0
Summary: Cloudera Iceberg MCP Server via Impala
License-File: LICENSE
License-File: NOTICE.txt
Requires-Python: >=3.13
Requires-Dist: fastmcp>=2.9.2
Requires-Dist: impyla>=0.21.0
Requires-Dist: mcp[cli]>=1.9.4
Requires-Dist: python-dotenv>=1.1.0
